{
  "movies": [
    {
      "id": "1",
      "title": "Tom & Jerry: Uma Aventura no Museu",
      "slug": "tom-e-jerry-uma-aventura-no-museu",
      "originalTitle": "Tom and Jerry: Forbidden Compass",
      "releaseDate": "08/01/2026",
      "synopsis": "A dupla mais famosa do mundo está de volta! Tom & Jerry se envolvem em mais uma de suas aventuras quando, durante uma perseguição dentro de um museu, eles encontram um objeto mágico e acabam sendo transportados no tempo. Perdidos em uma época distante e vivendo muitas confusões pelo caminho, eles precisarão deixar as brigas de lado e trabalhar juntos para encontrar um jeito de voltar para casa antes que seja tarde.",
      "cast": [
        "Li Baixin",
        "Zhang Gang",
        "Jiang Wen Jin",
        "Hanlin Li",
        "Xiongfei Tu",
        "Zhang Wenjie",
        "Shun Zi"
      ],
      "directors": [
        "Gang Zhang"
      ],
      "genres": [
        "Comédia",
        "Fantasia",
        "Família",
        "Aventura",
        "Animação"
      ],
      "contentRating": [
        "Violência fantasiosa"
      ],
      "duration": "01:39:00",
      "cover": "https://midias.imagemfilmes.com.br/capas/1bf2fef1-1f2f-4ec6-bf5e-476a5c5d0901_m.jpg",
      "trailer": "http://www.youtube.com/embed/kae_1CwyqTo",
      "gallery": [
        "https://midias.imagemfilmes.com.br/fotos/9ad9f839-e8fc-4835-a8dd-0cf438b43b94_thumb.jpg",
        "https://midias.imagemfilmes.com.br/fotos/aeaeaabb-9419-4a76-a3c9-72296d03352b_thumb.jpg",
        "https://midias.imagemfilmes.com.br/fotos/c3828c02-23ff-465a-809d-cbe1cfb9a154_thumb.jpg",
        "https://midias.imagemfilmes.com.br/fotos/1c099e08-13b2-403e-977d-1cc92ec87ea7_thumb.jpg",
        "https://midias.imagemfilmes.com.br/fotos/76fe67ea-21c9-457c-8371-d6369a76b2f6_thumb.jpg",
        "https://midias.imagemfilmes.com.br/fotos/88e54b47-ca95-450f-9ec3-a09987efc802_thumb.jpg",
        "https://midias.imagemfilmes.com.br/fotos/92654e25-cbb0-443a-b5cc-8a73be60980a_thumb.jpg",
        "https://midias.imagemfilmes.com.br/fotos/f53876ed-8a92-413c-bb0e-2c9dc589d7be_thumb.jpg"
      ]
    },
    {
      "id": "2",
      "title": "Deu Preguiça",
      "slug": "deu-preguica",
      "originalTitle": "The Sloth Lane",
      "releaseDate": "24/04/2025",
      "synopsis": "Após uma tempestade destruir seu lar, uma família de preguiças liderada por Gabriella (Heloísa Périssé) é forçada a se mudar para a agitada cidade grande, levando consigo seu food truck e um antigo livro de receitas. Deixando para trás a vida tranquila e guiados pela energia da jovem Laura (Tontom), eles embarcam nessa aventura com uma missão: mostrar que, nesta família, o prato principal é a diversão! Mas quando a ambiciosa empresária Dotti coloca os olhos nas preciosas receitas da família, eles terão que se unir para proteger suas tradições e tudo aquilo que acreditam.",
      "cast": [
        "Leslie Jones (Dotti Pace)",
        "Remy Hii (Platy)",
        "Olivia Vásquez (Gabriella)",
        "Teo Vergara (Laura)",
        "Dan Brumm (Chief Furbank)",
        "Ben Gorroño (Luis)",
        "Facundo Hache Herrera (Mani)",
        "Matteo Romaniuk (Arlo)",
        "Thalia Colettis (Additional Voices)",
        "Benjamin Gorroño (Luis)",
        "Andrew Cook (Coach Jerry)"
      ],
      "directors": [
        "Ricard Cussó",
        "Tania Vincent"
      ],
      "genres": [
        "Família",
        "Aventura",
        "Animação"
      ],
      "contentRating": "Violência fantasiosa",
      "duration": "01:29:00",
      "platforms": [
        {
          "name": "Apple iTunes",
          "url": "https://itunes.apple.com/br/movie/deu-pregui%C3%A7a/id1806228120"
        },
        {
          "name": "Net Now",
          "url": "https://www.clarotvmais.com.br/filme/deu-preguica/3271192"
        },
        {
          "name": "Prime Video",
          "url": "https://www.primevideo.com/-/pt/detail/0TN2TEN4QUVPQ01BANJQ12H088/ref=atv_sr_fle_c_Tn74RA_1_1_1?sr=1-1&pageTypeIdSource=ASIN&pageTypeId=B0F385L2JN&qid=1746647540439"
        },
        {
          "name": "Vivo",
          "url": "https://www.vivotv.com.br/details/movie/deu-preguica-40201422"
        },
        {
          "name": "Youtube Filmes",
          "url": "https://www.youtube.com/watch?v=_AtR5cpIpok"
        }
      ],
      "cover": "https://midias.imagemfilmes.com.br/capas/a21efa2b-e426-48aa-9486-ed86647b4302_m.jpg",
      "trailer": "http://www.youtube.com/embed/t9394RyT6qo",
      "gallery": [
        "https://midias.imagemfilmes.com.br/fotos/b3e789cb-2c92-49f8-b4aa-a87d676633f5_thumb.jpg",
        "https://midias.imagemfilmes.com.br/fotos/ff9403bd-9944-403f-824d-6e1cd6e060f5_thumb.jpg",
        "https://midias.imagemfilmes.com.br/fotos/c79b4125-28d2-42d9-bf65-ce789bc7e319_thumb.jpg",
        "https://midias.imagemfilmes.com.br/fotos/c9c1701a-5fd1-4b0e-bad8-dc749b61b47e_thumb.jpg",
        "https://midias.imagemfilmes.com.br/fotos/b4de951b-c3b0-4a7e-a378-43b9ec0cf51e_thumb.jpg",
        "https://midias.imagemfilmes.com.br/fotos/dc5fa9a2-7fb0-433e-8bf6-74f4701fe160_thumb.jpg",
        "https://midias.imagemfilmes.com.br/fotos/2aabaf69-873c-4635-807a-21366579a670_thumb.jpg",
        "https://midias.imagemfilmes.com.br/fotos/b366e739-b12d-403a-8080-63ea1ec79daa_thumb.jpg",
        "https://midias.imagemfilmes.com.br/fotos/97c44951-c03a-4b56-af80-0d7598e06963_thumb.jpg",
        "https://midias.imagemfilmes.com.br/fotos/8bfbdd1c-a4be-40c4-bb44-96cdb08df3cb_thumb.jpg"
      ]
    },
    {
      "id": 4,
      "title": "As Aventuras de Gulliver",
      "originalTitle": "Gulliver Returns",
      "releaseDate": "16/03/2022",
      "synopsis": "O maior aventureiro de todos os tempos está de volta! Ao retornar à cidade de Lilliput, Gulliver descobre que muita coisa mudou desde a sua partida e que os moradores estão enfrentando a ameaça de um general com sede de vingança. Gulliver é a última esperança para salvar a cidade e terá que se esforçar para vencer esse desafio gigante.",
      "cover": "https://midias.imagemfilmes.com.br/capas/1476b02d-eb22-4f25-939f-74aefc14e233_m.jpg?2021-05-07T17:29:38.010431",
      "cast": [
        "Tyler Bunch (Frelok)",
        "Wayne Grayson (Gulliver)",
        "Alyson Leigh Rosenfeld (Marcy)",
        "Billy Bob Thompson (King)",
        "Tom Wayland (Postman)"
      ],
      "directors": "Ilya Maksimov",
      "genres": [
        "Fantasia",
        "Família",
        "Aventura",
        "Animação"
      ],
      "contentRating": "Violência fantasiosa",
      "duration": "01:30:00",
      "trailer": "https://www.youtube.com/embed/9_iFEs3hWV8?si=MFLyiSZ-VyrRfgKg",
      "slug": "as-aventuras-de-gulliver"
    },
    {
      "id": 7,
      "title": "Paddington 2",
      "originalTitle": "Paddington 2",
      "releaseDate": "18/04/2018",
      "synopsis": "Após ser adotado pela família Brown, Paddington se tornou muito popular em Windsor Gardens. É aniversário de 100 anos da tia Lucy e ele precisará da ajuda de todos na procura do presente perfeito. Ele encontra um livro único na loja de antiguidades, mas o livro é roubado. Paddington e sua família farão de tudo para descobrir o ladrão e recuperar o livro que guarda um grande segredo.",
      "cover": "https://midias.imagemfilmes.com.br/capas/176d334f-94e0-42a4-8a59-f3165633fe4c_m.jpg?2019-06-17T15:54:41.330753",
      "cast": [
        "Ben Whishaw (Paddington)",
        "Hugh Grant (Phoenix Buchanan)",
        "Hugh Bonneville (Henry Brown)",
        "Sally Hawkins (Mary Brown)",
        "Michael Gambon (Uncle Pastuzo)",
        "Imelda Staunton (Aunt Lucy)",
        "Madeleine Harris (Judy Brown)",
        "Samuel Joslin (Jonathan Brown)",
        "Julie Walters (Mrs Bird)",
        "Marie-France Alvarez (Mademoiselle Dubois)",
        "Sanjeev Bhaskar (Dr Jafri)",
        "Ben Miller (Colonel Lancaster)",
        "Jessica Hynes (Miss Kitts)",
        "Robbie Gee (Mr Barnes)",
        "Nicholas Woodeson (Insurance Company C.E.O.)",
        "Alex Jordan (Steve Visby)",
        "Stewart Gilchrist (Chakrabatics Instructor)",
        "Jim Broadbent (Mr Gruber)",
        "Enzo Squillino Jr. (Mr Giuseppe)",
        "Tom Conti (Judge Gerald Biggleswade)",
        "Louis Partridge",
        "Peter Capaldi"
      ],
      "directors": "Paul King",
      "genres": [
        "Comédia",
        "Fantasia",
        "Família",
        "Aventura"
      ],
      "contentRating": "Nenhuma",
      "duration": "01:44:00",
      "trailer": "https://www.youtube.com/embed/52x5HJ9H8DM?si=7xakNHsz2FQi_Z3Q",
      "slug": "paddington-2"
    },
    {
      "id": 7,
      "title": "Elio",
      "originalTitle": "Elio",
      "releaseDate": "19/06/2025",
      "synopsis": "Elio (Yonas Kibreab) é um menino de 11 anos extremamente sonhador, artístico e criativo. Sua dificuldade em se encaixar o torna um garoto solitário, mas muito imaginativo. Sua fascinação pelo espaço e sua obsessão por aliens e vida fora da Terra acabam o levando por engano para Comuniverso, um reino onde opera uma organização interplanetária que abriga representantes de múltiplas e diferentes galáxias. A aventura dos sonhos de Elio começa e rapidamente ele é confundido pelas criaturas como o embaixador e líder da Terra. A partir daí, o menino precisa superar confusões e crises intergalácticas, formar laços com vidas alienígenas e descobrir quem ele realmente é e qual é o seu verdadeiro destino.",
      "cover": "https://lumiere-a.akamaihd.net/v1/images/image003_312ecbc3.jpeg?region=0,0,734,1047",
      "cast": [
        "Yonas Kibreab",
        "Zoe Saldana",
        "Jameela Jamil"
      ],
      "directors": [
        "Madeline Sharafian",
        "Domee Shi",
        "Adrian Molina"
      ],
      "genres": [
        "Animação",
        "Família"
      ],
      "contentRating": "Nenhuma",
      "duration": "01:39:00",
      "trailer": "https://www.youtube.com/embed/sAiWywScOMU?si=j_zBWGVDzEEVcmk9",
      "slug": "elio"
    },
    {
      "id": 7,
      "title": "Zootopia 2",
      "originalTitle": "Zootopia 2",
      "releaseDate": "27/11/2025",
      "synopsis": "Os heróis e policiais novatos Judy Hopps e Nick Wilde estão de volta para mais uma aventura extravagante pela grande metrópole animal de Zootopia. Em Zootopia 2, após desvendarem o maior caso da história da cidade, Judy e Nick são surpreendidos por uma ordem do Chefe Bogo: os dois detetives precisarão frequentar o programa de aconselhamento Parceiros em Crise. A união da dupla é colocada à prova quando surge um mistério ligado a um recém-chegado à cidade: o misterioso e venenoso réptil Gary De’Snake. Para encontrar as soluções para o caso envolvendo a víbora, Judy e Nick devem desvendar novas partes da cidade, sendo testados o tempo todo.",
      "cover": "https://lumiere-a.akamaihd.net/v1/images/image003_90a26c13.jpeg?region=0,0,770,1100",
      "cast": [
        "Monica Iozzi",
        "Ginnifer Goodwin",
        "Rodrigo Lombardi"
      ],
      "directors": [
        "Jared Bush",
        "Byron Howard"
      ],
      "genres": [
        "Animação",
        "Aventura",
        "Comédia"
      ],
      "contentRating": "Nenhuma",
      "duration": "01:48:00",
      "trailer": "https://www.youtube.com/embed/_UmBPK3D6X4?si=6N8X1YVLr0XHQ2Y3",
      "slug": "zootopia-2"
    },
    {
      "id": 7,
      "title": "Os Caras Malvados 2",
      "originalTitle": "The Bad Guys 2",
      "releaseDate": "14/08/2025",
      "synopsis": "O grupo de animais criminosos volta à ação, mas agora repaginados. Em Os Caras Malvados 2, cinco anos após os eventos do primeiro filme, Sr. Lobo e sua trupe infame de foras-da-lei decidiram abandonar o crime e se tornarem bons cidadãos, precisando aprender a lidar com as consequências dessa decisão. É mais difícil do que esperavam, lutando continuamente para ganharem a confiança e a aceitação das pessoas. Uma nova aventura surge, porém, quando um esquadrão de mulheres bandidas os força a fazer um serviço perigoso. Será preciso, então, dar uma pausa na aposentadoria para realizar o que dizem ser seu último trabalho.",
      "cover": "https://www.universalpics.com.br/tl_files/content/movies/bad_guys_2/posters/02.jpg",
      "cast": [
        "Sam Rockwell",
        "Craig Robinson",
        "Anthony Ramos"
      ],
      "directors": [
        "Pierre Perifel",
        "Juan Pablo Sans"
      ],
      "genres": [
        "Animação",
        "Aventura",
        "Comédia",
        "Família"
      ],
      "contentRating": "Violência fantasiosa",
      "duration": "01:44:00",
      "trailer": "https://www.youtube.com/embed/DccewDgXihs?si=NcIKKNBvOXg0eRxV",
      "slug": "os-caras-malvados-2"
    },
    {
      "id": 7,
      "title": "Divertidamente 2",
      "originalTitle": "Inside Out 2",
      "releaseDate": "20/06/2024",
      "synopsis": "Divertidamente 2 marca a sequência da famosa história de Riley (Kaitlyn Dias). Com um salto temporal, a garota agora se encontra mais velha, com 13 anos de idade, passando pela tão temida pré-adolescência. Junto com o amadurecimento, a sala de controle mental da jovem também está passando por uma demolição para dar lugar a algo totalmente inesperado: novas emoções. As já conhecidas, Alegria (Amy Poehler), Tristeza (Phyllis Smith), Raiva (Lewis Black), Medo (Tony Hale) e Nojinho (Liza Lapira), que desde quando Riley é bebê, eles predominam a central de controle da garota em uma operação bem-sucedida, tendo algumas falhas no percurso como foi apresentado no primeiro filme. As antigas emoções não têm certeza de como se sentir e com agir quando novos inquilinos chegam ao local, sendo um deles a tão temida Ansiedade (Maya Hawke). Inveja (Ayo Edebiri), Tédio (Adèle Exarchopoulos) e Vergonha (Paul Walter Hauser) integrarão juntos com a Ansiedade na mente de Riley, assim como a Nostalgia (June Squibb) que aparecerá também.",
      "cover": "https://ingresso-a.akamaihd.net/prd/img/movie/divertida-mente-2/61ac248d-e3e6-4e33-9515-8ce0621a32fa.webp",
      "cast": [
        "Miá Mello",
        "Amy Poehler",
        "Isabella Guarnieri"
      ],
      "directors": "Kelsey Mann",
      "genres": [
        "Animação",
        "Aventura",
        "Comédia",
        "Família"
      ],
      "contentRating": "Nenhuma",
      "duration": "01:36:00",
      "trailer": "https://www.youtube.com/embed/yAZxx8t9zig?si=lG0ku-gLSNdmCIlE",
      "slug": "divertidamente-2"
    },
    {
      "id": 7,
      "title": "Robô Selvagem",
      "originalTitle": "The Wild Robot",
      "releaseDate": "10/10/2024",
      "synopsis": "Uma nave naufraga numa terra desabitada e dá início à aventura épica do robô Roz, a última unidade das chamadas ROZZUM ainda funcional e inteligente. Preso nesta ilha aparentemente sozinho, Roz precisa sobreviver às intempéries da floresta. Sua única esperança é se adaptar ao ambiente hostil e avesso às suas programações. Para isso, Roz passa a conviver com os animais aprendendo sobre a vida na selva e os modos de sobrevivência na natureza. É durante essa exploração que Roz encontra um filhote de ganso e estabelece como missão cuidá-lo. Desse laço inesperado com o bicho abandonado, Roz se aproxima de uma realidade nova e instigante, construindo uma relação harmoniosa com os animais nativos. Do mesmo diretor de Lilo & Stitch e Como Treinar o Seu Dragão, Robô Selvagem é uma história comovente sobre a convivência entre tecnologia e natureza e o significado de estar vivo.",
      "cover": "https://www.universalpics.com.br/tl_files/content/movies/wild_robot/posters/02.jpg",
      "cast": [
        "Lupita Nyong'o",
        "Pedro Pascal",
        "Kit Connor"
      ],
      "directors": "Chris Sanders",
      "genres": [
        "Animação",
        "Aventura",
        "Comédia",
        "Família"
      ],
      "contentRating": "Violência fantasiosa",
      "duration": "01:42:00",
      "trailer": "https://www.youtube.com/embed/TbLVc8fnw7c?si=ukLCi0DVfxtUUOuQ",
      "slug": "robô-selvagem"
    },
    {
      "id": 7,
      "title": "Flow",
      "originalTitle": "Straume",
      "releaseDate": "20/02/2025",
      "synopsis": "Em Flow, o mundo parece ter chegado ao fim, coberto apenas por vestígios da presença humana, mas sem nenhum por perto. O gato é um animal solitário que, um dia, enquanto é perseguido por uma manada de cães, vê seu lar ser devastado por uma grande enchente. Buscando uma forma de sobreviver após a inundação, ele enfrenta diferentes ameaças, até que encontra refúgio em um pequeno barco povoado por diversas espécies. Enquanto tentam fugir de toda essa situação hostil, os animais terão que se unir apesar de suas diferenças. Nesse veleiro, navegando por paisagens místicas e transbordantes, eles passam pelos desafios e perigos da adaptação a este novo cenário pós-apocalíptico. Flow acompanha uma aventura por entre as ruínas de um mundo inundado e destruído e os sobreviventes que buscam permanecer à deriva com a ajuda e esperança de cada um.",
      "cover": "https://cinepop.com.br/wp-content/uploads/2025/01/flow-poster.jpg.webp",
      "cast": "Nenhum",
      "directors": "Gints Zilbalodis",
      "genres": [
        "Animação",
        "Aventura",
        "Família",
        "Fantasia"
      ],
      "contentRating": "Nenhuma",
      "duration": "01:25:00",
      "trailer": "https://www.youtube.com/embed/6QTSPE80Mj8?si=520y75HpI3P-_YZ-",
      "slug": "flow"
    }
  ],
  "admins": [
    {
      "email": "kelcoolg@gmail.com",
      "password": "ifsp123@",
      "id": "4d4c"
    },
    {
      "email": "alves.lucca@aluno.ifsp.edu.br",
      "password": "ifsp123@",
      "id": "2a8f"
    },
    {
      "email": "yukilucca89@gmail.com",
      "password": "ifsp123@",
      "id": "c76b"
    }
  ]
}